nbrefactor/__init__.py
nbrefactor/cli.py
nbrefactor/datastructs/__init__.py
nbrefactor/datastructs/markdown_element.py
nbrefactor/datastructs/module_node.py
nbrefactor/datastructs/parsed_cell.py
nbrefactor/datastructs/unparsed_cell.py
nbrefactor/fileops/__init__.py
nbrefactor/fileops/reader.py
nbrefactor/fileops/utils.py
nbrefactor/fileops/writer.py
nbrefactor/processor/__init__.py
nbrefactor/processor/cda.py
nbrefactor/processor/parser.py
nbrefactor/processor/processor.py
nbrefactor/utils/__init__.py
nbrefactor/utils/argument_parsing.py
nbrefactor/utils/logging.py
nbrefactor/visualization/__init__.py
nbrefactor/visualization/plot_module_tree.py
nbrefactor-0.1.6.dist-info/LICENSE
nbrefactor-0.1.6.dist-info/METADATA
nbrefactor-0.1.6.dist-info/WHEEL
nbrefactor-0.1.6.dist-info/entry_points.txt
nbrefactor-0.1.6.dist-info/top_level.txt
nbrefactor-0.1.6.dist-info/RECORD
