Metadata-Version: 2.2
Name: nbrefactor
Version: 0.1.6
Summary: An automation tool to refactor Jupyter Notebooks to Python modules, with code dependency analysis.
Home-page: https://github.com/ThunderStruct/nbrefactor
Author: Mohamed Shahawy
Author-email: envious-citizen.0s@icloud.com
Project-URL: Bug Reports, https://github.com/ThunderStruct/nbrefactor/issues
Project-URL: Source, https://github.com/ThunderStruct/nbrefactor
Keywords: jupyter,notebook,refactor,python,cli
Classifier: Intended Audience :: Developers
Classifier: Intended Audience :: Science/Research
Classifier: Topic :: Software Development :: Code Generators
Classifier: Topic :: Scientific/Engineering :: Information Analysis
Classifier: Framework :: Jupyter
Classifier: Framework :: IPython
Classifier: License :: OSI Approved :: MIT License
Classifier: Programming Language :: Python :: 3.7
Classifier: Programming Language :: Python :: 3.8
Classifier: Programming Language :: Python :: 3.9
Classifier: Programming Language :: Python :: 3.10
Classifier: Operating System :: OS Independent
Requires-Python: >=3.7
License-File: LICENSE
Requires-Dist: graphviz
Requires-Dist: nbformat
Requires-Dist: tqdm
Dynamic: author
Dynamic: author-email
Dynamic: classifier
Dynamic: description
Dynamic: description-content-type
Dynamic: home-page
Dynamic: keywords
Dynamic: project-url
Dynamic: requires-dist
Dynamic: requires-python
Dynamic: summary
